[
{"deliver_day": 2, "order_id": 3000001, "sending_day": 1, "receiver": 1, "sender": 3, "product": 3001, "quantity": 1, "delivered": 0, "last_update": 1, "transaction_id": 1},
{"deliver_day": 3, "order_id": 1000001, "sending_day": 2, "receiver": 0, "sender": 1, "product": 1001, "quantity": 8, "delivered": 0, "last_update": 2, "transaction_id": 2},
{"deliver_day": 3, "order_id": 2000001, "sending_day": 2, "receiver": 1, "sender": 2, "product": 2001, "quantity": 1, "delivered": 0, "last_update": 2, "transaction_id": 3},
{"deliver_day": 4, "order_id": 3000002, "sending_day": 3, "receiver": 1, "sender": 3, "product": 3001, "quantity": 1, "delivered": 0, "last_update": 3, "transaction_id": 4},
{"deliver_day": 6, "order_id": 3000003, "sending_day": 5, "receiver": 1, "sender": 3, "product": 3001, "quantity": 1, "delivered": 0, "last_update": 5, "transaction_id": 5},
{"deliver_day": 6, "order_id": 4000001, "sending_day": 5, "receiver": 3, "sender": 4, "product": 4001, "quantity": 1, "delivered": 0, "last_update": 5, "transaction_id": 6},
{"deliver_day": 7, "order_id": 1000002, "sending_day": 6, "receiver": 0, "sender": 1, "product": 1001, "quantity": 5, "delivered": 0, "last_update": 6, "transaction_id": 7},
{"deliver_day": 7, "order_id": 2000002, "sending_day": 6, "receiver": 1, "sender": 2, "product": 2001, "quantity": 1, "delivered": 0, "last_update": 6, "transaction_id": 8},
{"deliver_day": 8, "order_id": 2000003, "sending_day": 7, "receiver": 1, "sender": 2, "product": 2001, "quantity": 1, "delivered": 0, "last_update": 7, "transaction_id": 9},
{"deliver_day": 8, "order_id": 3000004, "sending_day": 7, "receiver": 1, "sender": 3, "product": 3001, "quantity": 1, "delivered": 0, "last_update": 7, "transaction_id": 10},
{"deliver_day": 8, "order_id": 3000005, "sending_day": 7, "receiver": 2, "sender": 3, "product": 3001, "quantity": 1, "delivered": 0, "last_update": 7, "transaction_id": 11},
{"deliver_day": 8, "order_id": 4000002, "sending_day": 7, "receiver": 3, "sender": 4, "product": 4001, "quantity": 1, "delivered": 0, "last_update": 7, "transaction_id": 12},
{"deliver_day": 9, "order_id": 1000003, "sending_day": 8, "receiver": 0, "sender": 1, "product": 1001, "quantity": 2, "delivered": 0, "last_update": 8, "transaction_id": 13},
{"deliver_day": 9, "order_id": 2000004, "sending_day": 8, "receiver": 1, "sender": 2, "product": 2001, "quantity": 1, "delivered": 0, "last_update": 8, "transaction_id": 14},
{"deliver_day": 9, "order_id": 3000006, "sending_day": 8, "receiver": 2, "sender": 3, "product": 3001, "quantity": 1, "delivered": 0, "last_update": 8, "transaction_id": 15},
{"deliver_day": 9, "order_id": 4000003, "sending_day": 8, "receiver": 3, "sender": 4, "product": 4001, "quantity": 1, "delivered": 0, "last_update": 8, "transaction_id": 16},
{"deliver_day": 9, "order_id": 5000001, "sending_day": 8, "receiver": 4, "sender": 5, "product": 5001, "quantity": 1, "delivered": 0, "last_update": 8, "transaction_id": 17},